tiny_brave/__init__.py
tiny_brave/client.py
tiny_brave/constants.py
tiny_brave/exceptions.py
tiny_brave/register.py
tiny_brave/tools.py
tiny_brave/datamodels/endpoints.py
tiny_brave/datamodels/requests/base.py
tiny_brave/datamodels/requests/images.py
tiny_brave/datamodels/requests/news.py
tiny_brave/datamodels/requests/videos.py
tiny_brave/datamodels/requests/web.py
tiny_brave/datamodels/responses/images.py
tiny_brave/datamodels/responses/news.py
tiny_brave/datamodels/responses/videos.py
tiny_brave/datamodels/responses/web.py
tinygent_brave-0.1.1007.dist-info/METADATA
tinygent_brave-0.1.1007.dist-info/WHEEL
tinygent_brave-0.1.1007.dist-info/entry_points.txt
tinygent_brave-0.1.1007.dist-info/RECORD
