Metadata-Version: 2.4
Name: tinygent-brave
Version: 0.1.1007
Requires-Dist: httpx>=0.28.1
Requires-Dist: pydantic>=2.11.7
Requires-Dist: tinygent
